README.md
setup.py
stockx_api_client/__init__.py
stockx_api_client/client.py
stockx_api_client/resources.py
stockx_api_client/utils.py
stockx_api_client.egg-info/PKG-INFO
stockx_api_client.egg-info/SOURCES.txt
stockx_api_client.egg-info/dependency_links.txt
stockx_api_client.egg-info/top_level.txt