Metadata-Version: 2.1
Name: stockx-api-client
Version: 0.0.2
Summary: A simple api client for stockx plateform
Home-page: https://github.com/sathouel/stockx-api-client.git
Author: Steven Athouel
Author-email: sathouel@gmail.com
License: UNKNOWN
Platform: UNKNOWN
Classifier: Programming Language :: Python :: 3
Classifier: License :: OSI Approved :: MIT License
Classifier: Operating System :: OS Independent
Requires-Python: >=3.6
